[{"ModuleName":"Conv_L","FuncActivationName":null,"PoolingType":null,"MatrixSize":15,"ModuleId":1,"Padding":1,"OutputSize":0,"PoolScale":0,"FilterCount":32,"FilterDepth":1},{"ModuleName":"Active_L","FuncActivationName":"relu","PoolingType":null,"MatrixSize":0,"ModuleId":2,"Padding":0,"OutputSize":0,"PoolScale":0,"FilterCount":0,"FilterDepth":0},{"ModuleName":"Pool_L","FuncActivationName":null,"PoolingType":"maxpooling","MatrixSize":2,"ModuleId":3,"Padding":0,"OutputSize":0,"PoolScale":2,"FilterCount":0,"FilterDepth":0},{"ModuleName":"Conv_L","FuncActivationName":null,"PoolingType":null,"MatrixSize":15,"ModuleId":1,"Padding":1,"OutputSize":0,"PoolScale":0,"FilterCount":64,"FilterDepth":1},{"ModuleName":"Active_L","FuncActivationName":"relu","PoolingType":null,"MatrixSize":0,"ModuleId":2,"Padding":0,"OutputSize":0,"PoolScale":0,"FilterCount":0,"FilterDepth":0},{"ModuleName":"Pool_L","FuncActivationName":null,"PoolingType":"maxpooling","MatrixSize":2,"ModuleId":3,"Padding":0,"OutputSize":0,"PoolScale":2,"FilterCount":0,"FilterDepth":0},{"ModuleName":"Conv_L","FuncActivationName":null,"PoolingType":null,"MatrixSize":15,"ModuleId":1,"Padding":1,"OutputSize":0,"PoolScale":0,"FilterCount":64,"FilterDepth":1},{"ModuleName":"Active_L","FuncActivationName":"relu","PoolingType":null,"MatrixSize":0,"ModuleId":2,"Padding":0,"OutputSize":0,"PoolScale":0,"FilterCount":0,"FilterDepth":0}]